symbolicwisardpkg.cp312-win_amd64.pyd
symbolicwisardpkg-0.1.6.dist-info/LICENSE.txt
symbolicwisardpkg-0.1.6.dist-info/METADATA
symbolicwisardpkg-0.1.6.dist-info/WHEEL
symbolicwisardpkg-0.1.6.dist-info/top_level.txt
symbolicwisardpkg-0.1.6.dist-info/RECORD
