Metadata-Version: 2.1
Name: symbolicwisardpkg
Version: 0.1.6
Summary: This project is an extension of the wisardpkg library and provides additional machine learning models based on the WiSARD architecture, including symbolic capabilities. It offers implementations of WiSARD-based models with high performance, easy installation, and a unified usage pattern.
Home-page: https://github.com/YasminForestti/wisardpkg-symbolic
Author: Yasmin Forestti Romeiro
Author-email: y.f.romeiro@gmail.com
Keywords: wisard,weithgless,neural,net,symbolic
Classifier: License :: OSI Approved :: MIT License
License-File: LICENSE.txt
Requires-Dist: pybind11>=2.2
